odoo/addons/account_invoice_inter_company/README.rst
odoo/addons/account_invoice_inter_company/__init__.py
odoo/addons/account_invoice_inter_company/__manifest__.py
odoo/addons/account_invoice_inter_company/i18n/account_invoice_inter_company.pot
odoo/addons/account_invoice_inter_company/i18n/de.po
odoo/addons/account_invoice_inter_company/i18n/es.po
odoo/addons/account_invoice_inter_company/i18n/es_AR.po
odoo/addons/account_invoice_inter_company/i18n/fr.po
odoo/addons/account_invoice_inter_company/i18n/hr.po
odoo/addons/account_invoice_inter_company/i18n/it.po
odoo/addons/account_invoice_inter_company/i18n/zh_CN.po
odoo/addons/account_invoice_inter_company/migrations/13.0.1.0.0/post-migration.py
odoo/addons/account_invoice_inter_company/models/__init__.py
odoo/addons/account_invoice_inter_company/models/account_move.py
odoo/addons/account_invoice_inter_company/models/res_company.py
odoo/addons/account_invoice_inter_company/models/res_config_settings.py
odoo/addons/account_invoice_inter_company/readme/CONFIGURE.rst
odoo/addons/account_invoice_inter_company/readme/CONTRIBUTORS.rst
odoo/addons/account_invoice_inter_company/readme/DESCRIPTION.rst
odoo/addons/account_invoice_inter_company/readme/ROADMAP.rst
odoo/addons/account_invoice_inter_company/static/description/icon.png
odoo/addons/account_invoice_inter_company/static/description/index.html
odoo/addons/account_invoice_inter_company/tests/__init__.py
odoo/addons/account_invoice_inter_company/tests/test_inter_company_invoice.py
odoo/addons/account_invoice_inter_company/views/account_move_views.xml
odoo/addons/account_invoice_inter_company/views/res_config_settings_view.xml
odoo13_addon_account_invoice_inter_company-13.0.2.1.4.dist-info/METADATA
odoo13_addon_account_invoice_inter_company-13.0.2.1.4.dist-info/WHEEL
odoo13_addon_account_invoice_inter_company-13.0.2.1.4.dist-info/top_level.txt
odoo13_addon_account_invoice_inter_company-13.0.2.1.4.dist-info/RECORD
